{
  "formatVersion": 1,
  "database": {
    "version": 3,
    "identityHash": "b33e353c18d35a07da4922215bbc1c9d",
    "entities": [
      {
        "tableName": "devices",
        "createSql": "CREATE TABLE IF NOT EXISTS `${TABLE_NAME}` (`id` INTEGER PRIMARY KEY AUTOINCREMENT NOT NULL, `device_name` TEXT, `device_ip` TEXT, `device_port` TEXT, `device_connectivity` TEXT, `device_on` INTEGER)",
        "fields": [
          {
            "fieldPath": "id",
            "columnName": "id",
            "affinity": "INTEGER",
            "notNull": true
          },
          {
            "fieldPath": "device",
            "columnName": "device_name",
            "affinity": "TEXT",
            "notNull": false
          },
          {
            "fieldPath": "ip",
            "columnName": "device_ip",
            "affinity": "TEXT",
            "notNull": false
          },
          {
            "fieldPath": "port",
            "columnName": "device_port",
            "affinity": "TEXT",
            "notNull": false
          },
          {
            "fieldPath": "connectivity",
            "columnName": "device_connectivity",
            "affinity": "TEXT",
            "notNull": false
          },
          {
            "fieldPath": "on",
            "columnName": "device_on",
            "affinity": "INTEGER",
            "notNull": false
          }
        ],
        "primaryKey": {
          "columnNames": [
            "id"
          ],
          "autoGenerate": true
        },
        "indices": [],
        "foreignKeys": []
      }
    ],
    "views": [],
    "setupQueries": [
      "CREATE TABLE IF NOT EXISTS room_master_table (id INTEGER PRIMARY KEY,identity_hash TEXT)",
      "INSERT OR REPLACE INTO room_master_table (id,identity_hash) VALUES(42, \"b33e353c18d35a07da4922215bbc1c9d\")"
    ]
  }
}